weidmd/__init__.py
weidmd/bopdmd.py
weidmd/cdmd.py
weidmd/dmd.py
weidmd/dmdbase.py
weidmd/dmdoperator.py
weidmd/hankeldmd.py
weidmd/hodmd.py
weidmd/meta.py
weidmd/rdmd.py
weidmd/snapshots.py
weidmd/utils.py
weidmd/weidmd.py
weidmd-0.0.2.dist-info/LICENSE
weidmd-0.0.2.dist-info/METADATA
weidmd-0.0.2.dist-info/WHEEL
weidmd-0.0.2.dist-info/top_level.txt
weidmd-0.0.2.dist-info/RECORD
